{
  "pages": [
    {
      "url": "https://sprunki.org/sprunki-3d-escape",
      "priority": 0.8,
      "last_modified": null,
      "change_frequency": "daily",
      "news_story": null
    },
    {
      "url": "https://sprunki.org/geometry-rush-4d",
      "priority": 0.8,
      "last_modified": null,
      "change_frequency": "daily",
      "news_story": null
    },
    {
      "url": "https://sprunki.org/music-festival",
      "priority": 0.8,
      "last_modified": null,
      "change_frequency": "daily",
      "news_story": null
    },
    {
      "url": "https://sprunki.org/friday-night-sprunki",
      "priority": 0.8,
      "last_modified": null,
      "change_frequency": "daily",
      "news_story": null
    },
    {
      "url": "https://sprunki.org/miside",
      "priority": 0.8,
      "last_modified": null,
      "change_frequency": "daily",
      "news_story": null
    }
  ]
}