{
  "pages": [
    {
      "url": "https://sprunki.com/egneodunq",
      "priority": 0.0,
      "last_modified": null,
      "change_frequency": "never",
      "news_story": null
    },
    {
      "url": "https://sprunki.com/qhqzf",
      "priority": 0.0,
      "last_modified": null,
      "change_frequency": "never",
      "news_story": null
    },
    {
      "url": "https://sprunki.com/5/",
      "priority": 0.0,
      "last_modified": null,
      "change_frequency": "never",
      "news_story": null
    },
    {
      "url": "https://sprunki.com/Incredibox-V9",
      "priority": 0.0,
      "last_modified": null,
      "change_frequency": "never",
      "news_story": null
    },
    {
      "url": "https://sprunki.com/4/",
      "priority": 0.0,
      "last_modified": null,
      "change_frequency": "never",
      "news_story": null
    },
    {
      "url": "https://sprunki.com/Incredibox-V2",
      "priority": 0.0,
      "last_modified": null,
      "change_frequency": "never",
      "news_story": null
    },
    {
      "url": "https://sprunki.com/Incredibox-V4",
      "priority": 0.0,
      "last_modified": null,
      "change_frequency": "never",
      "news_story": null
    },
    {
      "url": "https://sprunki.com/Incredibox-V5",
      "priority": 0.0,
      "last_modified": null,
      "change_frequency": "never",
      "news_story": null
    },
    {
      "url": "https://sprunki.com/Incredibox-V3",
      "priority": 0.0,
      "last_modified": null,
      "change_frequency": "never",
      "news_story": null
    },
    {
      "url": "https://sprunki.com/Incredibox-V8",
      "priority": 0.0,
      "last_modified": null,
      "change_frequency": "never",
      "news_story": null
    },
    {
      "url": "https://sprunki.com/oazfqzfe/e/m7/7q/0q/op3532np32m6204n055pp7pp36/01027922412470.bzs",
      "priority": 0.0,
      "last_modified": null,
      "change_frequency": "never",
      "news_story": null
    },
    {
      "url": "https://sprunki.com/3nF/27yVr/qjfdm.tfyx",
      "priority": 0.0,
      "last_modified": null,
      "change_frequency": "never",
      "news_story": null
    },
    {
      "url": "https://sprunki.com/oazfqzfe/e/m7/7q/0q/op3532np32m6204n055pp7pp36/01027922412471.bzs",
      "priority": 0.0,
      "last_modified": null,
      "change_frequency": "never",
      "news_story": null
    },
    {
      "url": "https://sprunki.com/Incredibox-V7",
      "priority": 0.0,
      "last_modified": null,
      "change_frequency": "never",
      "news_story": null
    },
    {
      "url": "https://sprunki.com/Incredibox-V1",
      "priority": 0.0,
      "last_modified": null,
      "change_frequency": "never",
      "news_story": null
    },
    {
      "url": "https://sprunki.com/Incredibox",
      "priority": 0.0,
      "last_modified": null,
      "change_frequency": "never",
      "news_story": null
    }
  ]
}